pipes/__init__.py
standard_pipes-3.13.0.dist-info/LICENSE
standard_pipes-3.13.0.dist-info/METADATA
standard_pipes-3.13.0.dist-info/WHEEL
standard_pipes-3.13.0.dist-info/top_level.txt
standard_pipes-3.13.0.dist-info/RECORD
