Metadata-Version: 2.1
Name: standard-pipes
Version: 3.13.0
Summary: Standard library pipes redistribution. "dead battery".
Author-email: Python Developers <python-deadlib@youknowone.org>
License: PSF-2.0
Project-URL: Homepage, https://github.com/youknowone/python-deadlib
Keywords: stdlib
Classifier: License :: OSI Approved :: Python Software Foundation License
Classifier: Topic :: Software Development :: Libraries
Classifier: Programming Language :: Python :: 3
License-File: LICENSE
